{
    "savedPatterns": {
        "images": [
            {
                "pattern1": "../images/bezierCurve/pattern1.png",
                "pattern2": "../images/bezierCurve/pattern2.png",
                "pattern3": "../images/bezierCurve/pattern3.png",
                "pattern4": "../images/bezierCurve/pattern4.png"
            }
        ],
        "pattern1":[
            {
                "x": 30,
                "y": 30
            },
            {
                "x": 70,
                "y": 200
            },
            {
                "x": 125,
                "y": 295
            },
            {
                "x": 350,
                "y": 350
            }
        ],
        "pattern2": [
            {
                "x": 120,
                "y": 303
            },
            {
                "x": 154,
                "y": 65
            },
            {
                "x": 426,
                "y": 65
            },
            {
                "x": 465,
                "y": 297
            }
        ],
        "pattern3": [
            {
                "x": 59,
                "y": 132
            },
            {
                "x": 143,
                "y": 430
            },
            {
                "x": 319,
                "y": 122
            },
            {
                "x": 481,
                "y": 327
            }
        ],
        "pattern4": [
            {
                "x": 170,
                "y": 320
            },
            {
                "x": 40,
                "y": 45
            },
            {
                "x": 210,
                "y": 45
            },
            {
                "x": 438,
                "y": 320
            }
        ]
    }
    
}